schedule_machine/__init__.py
schedule_machine/chrono.py
schedule_machine-0.1.0.dist-info/METADATA
schedule_machine-0.1.0.dist-info/WHEEL
schedule_machine-0.1.0.dist-info/top_level.txt
schedule_machine-0.1.0.dist-info/RECORD
