Metadata-Version: 2.1
Name: schedule-machine
Version: 0.1.0
Summary: A simple python scheduler
Home-page: https://github.com/BradKentAllen/schedule_machine
Author: Brad Allen - AditNW LLC
Author-email: brad.allen@aditnw.com
License: MIT
Platform: UNKNOWN
Classifier: License :: OSI Approved :: MIT License
Classifier: Programming Language :: Python :: 3
Classifier: Programming Language :: Python :: 3.7
Requires-Python: >=3.6
Requires-Dist: pytz
